INSTALL.txt
LICENSE.txt
MANIFEST.in
README
post_setup.py
setup.py
OSCAAR.egg-info/PKG-INFO
OSCAAR.egg-info/SOURCES.txt
OSCAAR.egg-info/dependency_links.txt
OSCAAR.egg-info/not-zip-safe
OSCAAR.egg-info/requires.txt
OSCAAR.egg-info/top_level.txt
docs/.DS_Store
docs/Makefile
docs/index.rst
docs/installation.rst
docs/make.bat
docs/modules.rst
docs/oscaar.astrometry.rst
docs/oscaar.c.rst
docs/oscaar.extras.eph.rst
docs/oscaar.extras.knownSystemParameters.rst
docs/oscaar.extras.rst
docs/oscaar.rst
docs/requirements.txt
docs/transiterDocumentation-20130522.pdf
docs/usage.rst
docs/documentationInProgress/.DS_Store
docs/documentationInProgress/documentation2.0.aux
docs/documentationInProgress/documentation2.0.log
docs/documentationInProgress/documentation2.0.out
docs/documentationInProgress/documentation2.0.pdf
docs/documentationInProgress/documentation2.0.synctex.gz
docs/documentationInProgress/documentation2.0.tex
docs/documentationInProgress/documentation2.0.toc
docs/documentationInProgress/imgs/.DS_Store
docs/documentationInProgress/imgs/GUI.png
docs/documentationInProgress/imgs/aperPlots.png
docs/documentationInProgress/imgs/coverpage.png
docs/documentationInProgress/imgs/ds9.png
docs/documentationInProgress/imgs/ds9gain.png
docs/documentationInProgress/imgs/ephemeris.png
docs/documentationInProgress/imgs/flatMaker.png
docs/documentationInProgress/imgs/focusing.png
docs/documentationInProgress/imgs/gui1.png
docs/documentationInProgress/imgs/gui2.png
docs/documentationInProgress/imgs/lightcurve.png
docs/documentationInProgress/imgs/logo2.png
docs/documentationInProgress/imgs/logoHUGEtile.png
docs/documentationInProgress/imgs/rawFluxes-eps-converted-to.pdf
docs/documentationInProgress/imgs/rawFluxes.eps
docs/documentationInProgress/imgs/sample.png
docs/documentationInProgress/imgs/scaledFluxes-eps-converted-to.pdf
docs/documentationInProgress/imgs/scaledFluxes.eps
docs/documentationInProgress/imgs/smooth-eps-converted-to.pdf
docs/documentationInProgress/imgs/smooth.eps
docs/documentationInProgress/imgs/smooth.png
docs/documentationInProgress/imgs/sums.png
docs/documentationInProgress/imgs/trackAperPlots.png
