Metadata-Version: 1.1
Name: OSCAAR
Version: 2.0beta
Summary: oscaar is an open source project aimed at helping you begin to study transiting extrasolar planets with differential photometry.
Home-page: https://github.com/OSCAAR/OSCAAR/wiki
Author: Core Developer: Brett M. Morris. Contributors: Daniel Galdi, Dharmatej Mikkilineni, Luuk Visser
Author-email: oscaarteam@gmail.com
License: LICENSE.txt
Download-URL: https://github.com/OSCAAR/OSCAAR/archive/master.zip
Keywords: oscaar transit astronomy photometry exoplanets
Platform: UNKNOWN
Classifier: Development Status :: 4 - Beta
Classifier: Intended Audience :: Science/Research
Classifier: License :: OSI Approved :: MIT License
Classifier: Operating System :: OS Independent
Classifier: Programming Language :: Python :: 2.7
Classifier: Programming Language :: C
Classifier: Topic :: Scientific/Engineering :: Astronomy
Classifier: Topic :: Scientific/Engineering :: Physics
